{
    "create_or_update_notebook": 
	{
		"keywords": ["notiz", "note", "schreib", "merk", "nachri", "eintrag", "erstell"],
		"init_prompt": "",
		"success_prompt": "Bestätige den erfolgreichen Eintrag ins Notizbuch.",
		"fail_prompt": ""
	},
	"delete_notebook_entry": 
	{
		"keywords": ["notiz", "note", "lösch", "entfer", "raus", "weg"],
		"init_prompt": "",
		"success_prompt": "Bestätige den erfolgreichen Eintrag ins Notizbuch.",
		"fail_prompt": ""
	},
	"return_notebook_entries": 
	{
		"keywords": ["notiz", "note", "gib", "eintr", "welch"],
		"init_prompt": "",
		"success_prompt": "Fasse zusammen ohne IDs.",
		"fail_prompt": ""
	},
	"change_notebook_name": 
	{
		"keywords": ["notiz", "note", "änder", "name"],
		"init_prompt": "",
		"success_prompt": "Bestätige das ändern des Namens.",
		"fail_prompt": ""
	},
	"switch_to_notebook": 
	{
		"keywords": ["notiz", "note", "wechs", "änder"],
		"init_prompt": "",
		"success_prompt": "Bestätige den erfolgreichen Wechsel des Notizbuchs.",
		"fail_prompt": ""
	},
	"list_all_notebook_names": 
	{
		"keywords": ["notiz", "note", "liste", "welch", "was", "verfüg"],
		"init_prompt": "",
		"success_prompt": "",
		"fail_prompt": ""
	}
}
