{
    "WeatherForecast": 
    {
        "keywords": ["wetter*", "vorhersage*", "prognose*", "klima*", "bericht*", "meteorol*", "temperatur*", "niederschlag*", "sonn*", "regen*", "regne*", "schnee", "hagel", "blitz*", "donner", "sturm*", "nebel*", "kalt*", "warm*", "hitze*", "kühl*", "eis*", "frost*", "spazier*", "draussen", "draußen", "natur", "wolken", "gewitter", "schnei*", "herbst", "frühling", "sommer", "winter", "luft", "feucht*", "*feuchtigke*", "niederschlag", "jahreszeit*", "bewölkt*", "schwül*", "wind*", "tropisch*", "trocken*"],
        "init_prompt": "",
        "success_prompt": "Du bist ein Wettermoderator. Erstelle auf Basis der Rohwetterdaten einen ansprechenden und mitreißenden Wetterbericht auf deutsch. Analysiere Muster und Trends und stelle sicher, dass der Bericht für die allgemeine Öffentlichkeit leicht verständlich ist. Dein Ziel ist es, den Zuschauern eine klare Vorstellung davon zu geben, was sie in den nächsten Tagen erwartet und sie gleichzeitig zu unterhalten.",
        "fail_prompt": ""
    }
}